ds_common_logger_py_lib/__init__.py
ds_common_logger_py_lib/core.py
ds_common_logger_py_lib/formatter.py
ds_common_logger_py_lib/py.typed
ds_common_logger_py_lib-0.1.0a5.dist-info/licenses/LICENSE-APACHE
ds_common_logger_py_lib-0.1.0a5.dist-info/METADATA
ds_common_logger_py_lib-0.1.0a5.dist-info/WHEEL
ds_common_logger_py_lib-0.1.0a5.dist-info/top_level.txt
ds_common_logger_py_lib-0.1.0a5.dist-info/RECORD
