Metadata-Version: 2.4
Name: ds-common-logger-py-lib
Version: 0.1.0a5
Summary: A Python package from the ds-common library collection
Author-email: Grasp Labs AS <hello@grasplabs.com>
Maintainer-email: Grasp Labs AS <hello@grasplabs.com>
License-Expression: Apache-2.0
Project-URL: Documentation, https://grasp-labs.github.io/ds-common-logger-py-lib/
Project-URL: Repository, https://github.com/grasp-labs/ds-common-logger-py-lib/
Project-URL: Issues, https://github.com/grasp-labs/ds-common-logger-py-lib/issues/
Project-URL: Changelog, https://github.com/grasp-labs/ds-common-logger-py-lib/releases
Keywords: ds,common,python
Classifier: Development Status :: 4 - Beta
Classifier: Programming Language :: Python :: 3
Classifier: Programming Language :: Python :: 3.10
Classifier: Programming Language :: Python :: 3.11
Classifier: Programming Language :: Python :: 3.12
Classifier: Programming Language :: Python :: 3.13
Classifier: Programming Language :: Python :: 3.14
Classifier: Operating System :: OS Independent
Classifier: Intended Audience :: Developers
Classifier: Topic :: Software Development :: Libraries :: Python Modules
Classifier: Topic :: System :: Logging
Requires-Python: >=3.10
License-File: LICENSE-APACHE
Provides-Extra: dev
Requires-Dist: ruff>=0.1.8; extra == "dev"
Requires-Dist: mypy>=1.7.0; extra == "dev"
Requires-Dist: pytest>=7.4.0; extra == "dev"
Requires-Dist: pytest-cov>=4.1.0; extra == "dev"
Requires-Dist: pytest-xdist>=3.3.0; extra == "dev"
Requires-Dist: pre-commit>=3.6.0; extra == "dev"
Requires-Dist: build>=1.0.0; extra == "dev"
Requires-Dist: twine>=4.0.0; extra == "dev"
Requires-Dist: sphinx>=7.1.0; extra == "dev"
Requires-Dist: sphinx-autoapi>=3.0.0; extra == "dev"
Requires-Dist: sphinx-material>=0.0.35; extra == "dev"
Requires-Dist: bandit>=1.7.0; extra == "dev"
Provides-Extra: test
Requires-Dist: pytest>=7.4.0; extra == "test"
Requires-Dist: pytest-cov>=4.1.0; extra == "test"
Requires-Dist: pytest-xdist>=3.3.0; extra == "test"
Provides-Extra: docs
Requires-Dist: sphinx>=7.1.0; extra == "docs"
Requires-Dist: sphinx-autoapi>=3.0.0; extra == "docs"
Requires-Dist: sphinx-material>=0.0.35; extra == "docs"
Dynamic: license-file
